plasmidcanvas/__init__.py
plasmidcanvas/_curvedtext.py
plasmidcanvas/_utils.py
plasmidcanvas/feature.py
plasmidcanvas/plasmid.py
plasmidcanvas/sequence.gb
plasmidcanvas-1.0.0.dist-info/LICENSE
plasmidcanvas-1.0.0.dist-info/METADATA
plasmidcanvas-1.0.0.dist-info/WHEEL
plasmidcanvas-1.0.0.dist-info/RECORD
